junkie/__init__.py
junkie/junkie.py
junkie/version.py
junkie_rfglab-2025.10.4.dist-info/licenses/LICENSE
junkie_rfglab-2025.10.4.dist-info/METADATA
junkie_rfglab-2025.10.4.dist-info/WHEEL
junkie_rfglab-2025.10.4.dist-info/top_level.txt
junkie_rfglab-2025.10.4.dist-info/RECORD
