Metadata-Version: 2.4
Name: junkie-rfglab
Version: 2025.10.4
Summary: junkie is a JUpyter NotebooK Image Explorer
Author-email: Rodrigo Fernandez-Gonzalez <rodrigo.fernandez.gonzalez@utoronto.ca>
License-Expression: GPL-3.0-or-later
Project-URL: Homepage, https://bitbucket.com/rfg_lab/junkie
Project-URL: Bug Tracker, https://bitbucket.com/rfg_lab/junkie/issues
Classifier: Programming Language :: Python :: 3.10
Classifier: Programming Language :: Python :: 3.11
Classifier: Programming Language :: Python :: 3.12
Classifier: Programming Language :: Python :: 3.13
Classifier: Operating System :: OS Independent
Requires-Python: >=3.10
License-File: LICENSE
Requires-Dist: numpy>=1.23
Requires-Dist: ipympl>=0.9
Requires-Dist: IPython>=9.5.0
Requires-Dist: ipywidgets>=8.0
Requires-Dist: matplotlib>=3.7
Requires-Dist: scipy>=1.16.1
Requires-Dist: scikit-image
Requires-Dist: tifffile>=2025.8.28
Dynamic: license-file
